datainsight/__init__.py
datainsight/app.py
datainsight-0.2.0.dist-info/LICENSE
datainsight-0.2.0.dist-info/METADATA
datainsight-0.2.0.dist-info/WHEEL
datainsight-0.2.0.dist-info/entry_points.txt
datainsight-0.2.0.dist-info/top_level.txt
datainsight-0.2.0.dist-info/RECORD
