Metadata-Version: 2.1
Name: datainsight
Version: 0.2.0
Summary: A Python package for CSV data analysis
Author-email: Ateendra Jha <ajha@chears.in>
License: MIT
Project-URL: Homepage, https://chears.in/contact
Project-URL: Issues, https://chears.in/contact
License-File: LICENSE
Requires-Dist: pandas
Requires-Dist: matplotlib
Requires-Dist: seaborn
Requires-Dist: streamlit
Requires-Dist: scikit-learn
Requires-Dist: python-docx
Requires-Dist: numpy
Requires-Dist: Pillow
